gnubg/__init__.py
gnubg/__version__.py
gnubg/gnubg.cpython-311-x86_64-linux-gnu.so
gnubg/data/gnubg.weights
gnubg/data/gnubg_os.db
gnubg/data/gnubg_os0.bd
gnubg/data/gnubg_ts0.bd
gnubg-1.1.0a1.dist-info/METADATA
gnubg-1.1.0a1.dist-info/WHEEL
gnubg-1.1.0a1.dist-info/RECORD
gnubg-1.1.0a1.dist-info/licenses/LICENSE
