Metadata-Version: 2.4
Name: gnubg
Version: 1.1.0a1
Summary: Python3 bindings for GNUBG neural evaluation
Author-Email: David Reay <dr323090@falmouth.ac.uk>
License-File: LICENSE
Project-URL: Homepage, https://www.gnu.org/software/gnubg/
Project-URL: Documentation, http://www.gnubg.org/documentation/doku.php?id=gnu_backgammon_faq
Project-URL: Source, https://github.com/gnubg/gnubg-nn-pypi
Project-URL: GNUBG, https://git.savannah.gnu.org/cgit/gnubg/gnubg-nn.git
Project-URL: MailingList, https://lists.gnu.org/mailman/listinfo/gnubg
Project-URL: Credits, https://git.savannah.gnu.org/cgit/gnubg.git/tree/credits.sh
Requires-Python: >=3.8
